{
    "oddsForTypesAvailable": ["4.0", "4.5","5.0", "6.0","4.0", "5.0","4.0", "INT 4.5","4.5","4.5","INT 5.0","4.0","6.0", "WOMEN", "4.5","5.0"],
    "4.0": [
        {
            "name":"Swansea City",
            "league":"England Premier League",
            "attack":"77",
            "midfield":"76",
            "defense":"76",
            "badge_url":""
        },
        {
            "name":"Celta Vigo",
            "league":"Spain BBVA",
            "attack":"77",
            "midfield":"76",
            "defense":"76",
            "badge_url":""
        },
        {
            "name":"Olym. Marseille",
            "league":"France League 1",
            "attack":"77",
            "midfield":"76",
            "defense":"74",
            "badge_url":""
        },
        {
            "name":"Torino",
            "league":"Italy Serie A",
            "attack":"77",
            "midfield":"75",
            "defense":"77",
            "badge_url":""
        },
        {
            "name":"Real Betis",
            "league":"Spain BBVA",
            "attack":"77",
            "midfield":"75",
            "defense":"75",
            "badge_url":""
        },
        {
            "name":"Leicester City",
            "league":"England Premier League",
            "attack":"76",
            "midfield":"77",
            "defense":"75",
            "badge_url":""
        },
        {
            "name":"Crystal Palace",
            "league":"England Premier League",
            "attack":"75",
            "midfield":"76",
            "defense":"75",
            "badge_url":""
        },
        {
            "name":"Malaga CF",
            "league":"Spain BBVA",
            "attack":"75",
            "midfield":"76",
            "defense":"75",
            "badge_url":""
        },
        {
            "name":"PSV",
            "league":"Netherlands Eredivisie",
            "attack":"",
            "midfield":"",
            "defense":"",
            "badge_url":""
        },
        {
            "name":"1899 Hoffenheim",
            "league":"Germany Bundesliga",
            "attack":"75",
            "midfield":"74",
            "defense":"75",
            "badge_url":""
        },
        {
            "name":"Shakhtar Donetsk",
            "league":"Ukraine",
            "attack":"74",
            "midfield":"76",
            "defense":"76",
            "badge_url":""
        },
        {
            "name":"Ajax",
            "league":"Netherlands Eredivisie",
            "attack":"74",
            "midfield":"76",
            "defense":"74",
            "badge_url":""
        },
        {
            "name":"AS Saint-Étienne",
            "league":"France League 1",
            "attack":"74",
            "midfield":"75",
            "defense":"76",
            "badge_url":""
        },
        {
            "name":"CSKA Moscow",
            "league":"Russian League",
            "attack":"72",
            "midfield":"78",
            "defense":"75",
            "badge_url":""
        },
        {
            "name":"RC Deportivo",
            "league":"Spain BBVA",
            "attack":"79",
            "midfield":"74",
            "defense":"74",
            "badge_url":""
        },
        {
            "name":"Watford",
            "league":"England Premier League",
            "attack":"77",
            "midfield":"74",
            "defense":"74",
            "badge_url":""
        },
        {
            "name":"Sunderland",
            "league":"England Premier League",
            "attack":"77",
            "midfield":"74",
            "defense":"74",
            "badge_url":""
        },
        {
            "name":"Stade Rennais",
            "league":"France League 1",
            "attack":"76",
            "midfield":"75",
            "defense":"75",
            "badge_url":""
        },
        {
            "name":"RCD Espanyol",
            "league":"Spain BBVA",
            "attack":"76",
            "midfield":"75",
            "defense":"74",
            "badge_url":""
        },
        {
            "name":"Levante UD",
            "league":"Spain BBVA",
            "attack":"76",
            "midfield":"75",
            "defense":"73",
            "badge_url":""
        },
        {
            "name":"Udinese",
            "league":"Italy Serie A",
            "attack":"76",
            "midfield":"74",
            "defense":"75",
            "badge_url":""
        },
        {
            "name":"Hamburger SV",
            "league":"Germany Bundesliga",
            "attack":"76",
            "midfield":"74",
            "defense":"74",
            "badge_url":""
        },
        {
            "name":"West Brom",
            "league":"England Premier League",
            "attack":"76",
            "midfield":"73",
            "defense":"73",
            "badge_url":""
        },
        {
            "name":"Eint. Frankfurt",
            "league":"Germany Bundesliga",
            "attack":"76",
            "midfield":"72",
            "defense":"73",
            "badge_url":""
        },
        {
            "name":"VfB Stuttgart",
            "league":"Germany Bundesliga",
            "attack":"75",
            "midfield":"76",
            "defense":"74",
            "badge_url":""
        },
        {
            "name":"Atl. Mineiro",
            "league":"Brasileirão",
            "attack":"75",
            "midfield":"75",
            "defense":"76",
            "badge_url":""
        },
        {
            "name":"Hertha BSC",
            "league":"Germany Bundesliga",
            "attack":"75",
            "midfield":"75",
            "defense":"76",
            "badge_url":""
        },
        {
            "name":"Rayo Vallencano",
            "league":"Spain BBVA",
            "attack":"75",
            "midfield":"75",
            "defense":"74",
            "badge_url":""
        },
        {
            "name":"Olympiakos CFP",
            "league":"Greece",
            "attack":"75",
            "midfield":"75",
            "defense":"74",
            "badge_url":""
        },
        {
            "name":"FSC Mainz 05",
            "league":"Germany Bundesliga",
            "attack":"75",
            "midfield":"75",
            "defense":"74",
            "badge_url":""
        },
        {
            "name":"FC Augsburg",
            "league":"Germany Bundesliga",
            "attack":"75",
            "midfield":"74",
            "defense":"73",
            "badge_url":""
        },
        {
            "name":"LOSC Lille",
            "league":"France League 1",
            "attack":"75",
            "midfield":"73",
            "defense":"76",
            "badge_url":""
        },
        {
            "name":"Sampdoria",
            "league":"Italy Serie A",
            "attack":"75",
            "midfield":"72",
            "defense":"73",
            "badge_url":""
        },
        {
            "name":"FC Krasnodar",
            "league":"Russian League",
            "attack":"74",
            "midfield":"75",
            "defense":"74",
            "badge_url":""
        },
        {
            "name":"Aston Villa",
            "league":"England Premier League",
            "attack":"74",
            "midfield":"74",
            "defense":"74",
            "badge_url":""
        },
        {
            "name":"FC Koln",
            "league":"Germany Bundesliga",
            "attack":"74",
            "midfield":"73",
            "defense":"74",
            "badge_url":""
        },
        {
            "name":"Genoa",
            "league":"Italy Serie A",
            "attack":"73",
            "midfield":"73",
            "defense":"75",
            "badge_url":""
        },
        {
            "name":"Galatasaray",
            "league":"Turkey Super Lig",
            "attack":"70",
            "midfield":"75",
            "defense":"73",
            "badge_url":""
        },
        {
            "name":"Lokomotiv Moscow",
            "league":"Russian League",
            "attack":"65",
            "midfield":"63",
            "defense":"75",
            "badge_url":""
        },
        {
            "name":"Norwich",
            "league":"England Premier League",
            "attack":"78",
            "midfield":"74",
            "defense":"73",
            "badge_url":""
        },
        {
            "name":"Sassuolo",
            "league":"Italy Serie A",
            "attack":"77",
            "midfield":"72",
            "defense":"74",
            "badge_url":""
        },
        {
            "name":"Werder Bremen",
            "league":"Germany Bundesliga",
            "attack":"76",
            "midfield":"70",
            "defense":"75",
            "badge_url":""
        },
        {
            "name":"SC Braga",
            "league":"Portugal Liga NOS",
            "attack":"75",
            "midfield":"74",
            "defense":"74",
            "badge_url":""
        },
        {
            "name":"Giron. Bordeaux",
            "league":"France League 1",
            "attack":"75",
            "midfield":"73",
            "defense":"74",
            "badge_url":""
        },
        {
            "name":"KAA Gent",
            "league":"Belgium Pro League",
            "attack":"75",
            "midfield":"73",
            "defense":"73",
            "badge_url":""
        },
        {
            "name":"Bologna",
            "league":"Italy Serie A",
            "attack":"75",
            "midfield":"72",
            "defense":"72",
            "badge_url":""
        },
        {
            "name":"OGC Nice",
            "league":"France League 1",
            "attack":"74",
            "midfield":"75",
            "defense":"74",
            "badge_url":""
        },
        {
            "name":"RSC Anderlecht",
            "league":"Belgium Pro League",
            "attack":"74",
            "midfield":"75",
            "defense":"72",
            "badge_url":""
        },
        {
            "name":"Boca Juniors",
            "league":"Argentina Primera Division",
            "attack":"74",
            "midfield":"74",
            "defense":"73",
            "badge_url":""
        },
        {
            "name":"Atalanta",
            "league":"Italy Serie A",
            "attack":"74",
            "midfield":"73",
            "defense":"73",
            "badge_url":""
        },
        {
            "name":"Getafe CF",
            "league":"Spain BBVA",
            "attack":"73",
            "midfield":"75",
            "defense":"74",
            "badge_url":""
        },
        {
            "name":"San Lorenzo",
            "league":"Argentina Primera Division",
            "attack":"73",
            "midfield":"74",
            "defense":"74",
            "badge_url":""
        },
        {
            "name":"Feyenoord",
            "league":"Netherlands Eredivisie",
            "attack":"73",
            "midfield":"74",
            "defense":"74",
            "badge_url":""
        },
        {
            "name":"Chievo Verona",
            "league":"Italy Serie A",
            "attack":"73",
            "midfield":"74",
            "defense":"73",
            "badge_url":""
        },
        {
            "name":"Granada CF",
            "league":"Italy Serie A",
            "attack":"73",
            "midfield":"73",
            "defense":"74",
            "badge_url":""
        },
        {
            "name":"Hannover 96",
            "league":"Germany Bundesliga",
            "attack":"73",
            "midfield":"70",
            "defense":"74",
            "badge_url":""
        },
        {
            "name":"River Plate",
            "league":"Argentina Primera Division",
            "attack":"72",
            "midfield":"74",
            "defense":"74",
            "badge_url":""
        }
    ],
    "4.5": [
        {
            "name":"Everton",
            "league":"England Premier League",
            "attack":"78",
            "midfield":"78",
            "defense":"80",
            "badge_url":""
        },
        {
            "name":"Liverpool",
            "league":"England Premier League",
            "attack":"81",
            "midfield":"79",
            "defense":"79",
            "badge_url":""
        },
        {
            "name":"Southampton",
            "league":"England Premier League",
            "attack":"76",
            "midfield":"76",
            "defense":"76",
            "badge_url":""
        },
        {
            "name":"Tottenham Spurs",
            "league":"England Premier League",
            "attack":"82",
            "midfield":"78",
            "defense":"79",
            "badge_url":""
        },
        {
            "name":"Valencia CF",
            "league":"Spain BBVA",
            "attack":"79",
            "midfield":"80",
            "defense":"79",
            "badge_url":""
        },
        {
            "name":"Napoli",
            "league":"Italy Serie A",
            "attack":"83",
            "midfield":"78",
            "defense":"79",
            "badge_url":""
        },
        {
            "name":"Roma",
            "league":"Italy Serie A",
            "attack":"79",
            "midfield":"82",
            "defense":"78",
            "badge_url":""
        },
        {
            "name":"Sevilla FC",
            "league":"Spain BBVA",
            "attack":"79",
            "midfield":"80",
            "defense":"80",
            "badge_url":""
        },
        {
            "name":"Villarreal CF",
            "league":"Spain BBVA",
            "attack":"79",
            "midfield":"79",
            "defense":"79",
            "badge_url":""
        },
        {
            "name":"Bayer 04",
            "league":"Germany Bundesliga",
            "attack":"79",
            "midfield":"76",
            "defense":"76",
            "badge_url":""
        },
        {
            "name":"Wolfsburg",
            "league":"Germany Bundesliga",
            "attack":"78",
            "midfield":"79",
            "defense":"79",
            "badge_url":""
        },
        {
            "name":"Internazzionale",
            "league":"Italy Serie A",
            "attack":"78",
            "midfield":"79",
            "defense":"78",
            "badge_url":""
        },  
        {
            "name":"Athletic Bilbao",
            "league":"Spain BBVA",
            "attack":"78",
            "midfield":"78",
            "defense":"78",
            "badge_url":""
        },
        {
            "name":"Benfica",
            "league":"Portugal Liga NOS",
            "attack":"81",
            "midfield":"78",
            "defense":"77",
            "badge_url":""
        },
        {
            "name":"Sporting CP",
            "league":"Portugal Liga NOS",
            "attack":"79",
            "midfield":"79",
            "defense":"74",
            "badge_url":""
        },
        {
            "name":"Zenit",
            "league":"Russian League",
            "attack":"79",
            "midfield":"78",
            "defense":"78",
            "badge_url":""
        },
        {
            "name":"FC Schalke 04",
            "league":"Germany Bundesliga",
            "attack":"79",
            "midfield":"77",
            "defense":"78",
            "badge_url":""
        },
        {
            "name":"Milan",
            "league":"Italy Serie A",
            "attack":"79",
            "midfield":"75",
            "defense":"76",
            "badge_url":""
        },
        {
            "name":"Lazio",
            "league":"Italy Serie A",
            "attack":"78",
            "midfield":"77",
            "defense":"77",
            "badge_url":""
        },
        {
            "name":"FC Porto",
            "league":"Portugal Liga NOS",
            "attack":"77",
            "midfield":"78",
            "defense":"76",
            "badge_url":""
        },
        {
            "name":"Borussia M'gladbach",
            "league":"Germany Bundesliga",
            "attack":"77",
            "midfield":"78",
            "defense":"75",
            "badge_url":""
        },
        {
            "name":"Besiktas",
            "league":"Turkey Super Lig",
            "attack":"79",
            "midfield":"77",
            "defense":"75",
            "badge_url":""
        },
        {
            "name":"Fenerbahçe",
            "league":"Turkey Super Lig",
            "attack":"79",
            "midfield":"76",
            "defense":"76",
            "badge_url":""
        },
        {
            "name":"Fiorentina",
            "league":"Italy Serie A",
            "attack":"78",
            "midfield":"76",
            "defense":"78",
            "badge_url":""
        },
        {
            "name":"AS Monaco",
            "league":"France Ligue 1",
            "attack":"77",
            "midfield":"77",
            "defense":"77",
            "badge_url":""
        },
        {
            "name":"Olym. Lyonnais",
            "league":"France Ligue 1",
            "attack":"77",
            "midfield":"77",
            "defense":"77",
            "badge_url":""
        }, 
        {
            "name":"Real Sociedad",
            "league":"Spain BBVA",
            "attack":"77",
            "midfield":"77",
            "defense":"76",
            "badge_url":""
        },
        {
            "name":"Newcastle Utd",
            "league":"England Premier League",
            "attack":"77",
            "midfield":"77",
            "defense":"75",
            "badge_url":""
        },
        {
            "name":"Stoke City",
            "league":"England Premier League",
            "attack":"76",
            "midfield":"78",
            "defense":"76",
            "badge_url":""
        },
        {
            "name":"West Ham",
            "league":"England Premier League",
            "attack":"76",
            "midfield":"76",
            "defense":"74",
            "badge_url":""
        }  
    ],
    "5.0": [
        {
            "name":"Arsenal",
            "league":"England Premier League",
            "attack":"82",
            "midfield":"79",
            "defense":"80",
            "badge_url":""
        },
        {
            "name":"Chelsea",
            "league":"England Premier League",
            "attack":"81",
            "midfield":"82",
            "defense":"82",
            "badge_url":""
        },
        {
            "name":"Man. City",
            "league":"England Premier League",
            "attack":"84",
            "midfield":"82",
            "defense":"81",
            "badge_url":""
        },
        {
            "name":"Man. Utd",
            "league":"England Premier League",
            "attack":"69",
            "midfield":"80",
            "defense":"77",
            "badge_url":""
        },
        {
            "name":"PSG",
            "league":"France Ligue 1",
            "attack":"84",
            "midfield":"82",
            "defense":"82",
            "badge_url":""
        },
        {
            "name":"Juventus",
            "league":"Italy Serie A",
            "attack":"81",
            "midfield":"79",
            "defense":"83",
            "badge_url":""
        },
        {
            "name":"Dortmund",
            "league":"Germany Bundesliga",
            "attack":"84",
            "midfield":"81",
            "defense":"81",
            "badge_url":""
        },
        {
            "name":"Atl. Madrid",
            "league":"Spain BBVA",
            "attack":"81",
            "midfield":"80",
            "defense":"81",
            "badge_url":""
        }
    ],
    "6.0": [
        {
            "name":"Barcelona",
            "league":"Spain BBVA",
            "attack":"91",
            "midfield":"85",
            "defense":"82",
            "badge_url":""
        },
        {
            "name":"Real Madrid",
            "league":"Spain BBVA",
            "attack":"86",
            "midfield":"86",
            "defense":"83",
            "badge_url":""
        },
        {
            "name":"FC Bayern",
            "league":"Germany Bundesliga",
            "attack":"88",
            "midfield":"84",
            "defense":"84",
            "badge_url":""
        }
    ],
    "INT 4.5":[
        {
            "name":"Chile",
            "league":"International",
            "attack":"80",
            "midfield":"77",
            "defense":"75",
            "badge_url":""
        },
        {
            "name":"Russia",
            "league":"International",
            "attack":"78",
            "midfield":"76",
            "defense":"77",
            "badge_url":""
        },
        {
            "name":"Switzerland",
            "league":"International",
            "attack":"76",
            "midfield":"77",
            "defense":"78",
            "badge_url":""
        },
        {
            "name":"Turkey",
            "league":"International",
            "attack":"77",
            "midfield":"78",
            "defense":"76",
            "badge_url":""
        },
        {
            "name":"Mexico",
            "league":"International",
            "attack":"76",
            "midfield":"79",
            "defense":"76",
            "badge_url":""
        },
        {
            "name":"England",
            "league":"International",
            "attack":"81",
            "midfield":"79",
            "defense":"80",
            "badge_url":""
        },
        {
            "name":"Uruguay",
            "league":"International",
            "attack":"84",
            "midfield":"75",
            "defense":"77",
            "badge_url":""
        },
        {
            "name":"Netherlands",
            "league":"International",
            "attack":"81",
            "midfield":"78",
            "defense":"77",
            "badge_url":""
        }
    ],
    "INT 5.0":[
        {
            "name":"Brazil",
            "league":"International",
            "attack":"85",
            "midfield":"80",
            "defense":"84",
            "badge_url":""
        },
        {
            "name":"Argentina",
            "league":"International",
            "attack":"88",
            "midfield":"80",
            "defense":"77",
            "badge_url":""
        },
        {
            "name":"Belgium",
            "league":"International",
            "attack":"80",
            "midfield":"82",
            "defense":"77",
            "badge_url":""
        },
        {
            "name":"France",
            "league":"International",
            "attack":"82",
            "midfield":"82",
            "defense":"80",
            "badge_url":""
        },
        {
            "name":"Germany",
            "league":"International",
            "attack":"78",
            "midfield":"83",
            "defense":"82",
            "badge_url":""
        },
        {
            "name":"Italy",
            "league":"International",
            "attack":"79",
            "midfield":"79",
            "defense":"84",
            "badge_url":""
        },
        {
            "name":"Portugal",
            "league":"International",
            "attack":"85",
            "midfield":"80",
            "defense":"79",
            "badge_url":""
        },
        {
            "name":"Spain",
            "league":"International",
            "attack":"81",
            "midfield":"85",
            "defense":"83",
            "badge_url":""
        }
    ],
    "WOMEN":[
        {
            "name":"Brazil",
            "league":"Women International",
            "attack":"85",
            "midfield":"79",
            "defense":"75",
            "badge_url":""
        },
        {
            "name":"England",
            "league":"Women International",
            "attack":"75",
            "midfield":"75",
            "defense":"77",
            "badge_url":""
        },
        {
            "name":"France",
            "league":"Women International",
            "attack":"81",
            "midfield":"81",
            "defense":"79",
            "badge_url":""
        },
        {
            "name":"Sweden",
            "league":"Women International",
            "attack":"79",
            "midfield":"78",
            "defense":"75",
            "badge_url":""
        },
        {
            "name":"Germany",
            "league":"Women International",
            "attack":"82",
            "midfield":"74",
            "defense":"77",
            "badge_url":"http://i.imgur.com/KVV5CEY.png"
        },
        {
            "name":"United States",
            "league":"Women International",
            "attack":"79",
            "midfield":"84",
            "defense":"82",
            "badge_url":"http://i.imgur.com/TMtZzmQ.png"
        }  
    ]
}